motor_python/__init__.py
motor_python/__main__.py
motor_python/cube_mars_motor.py
motor_python/definitions.py
motor_python/examples.py
motor_python/motor_status_parser.py
motor_python/utils.py
motor_python-0.0.6.dist-info/METADATA
motor_python-0.0.6.dist-info/WHEEL
motor_python-0.0.6.dist-info/licenses/LICENSE
motor_python-0.0.6.dist-info/RECORD
