Metadata-Version: 2.4
Name: motor_python
Version: 0.0.6
Summary: CubeMars motor module for Aries exosuits.
Project-URL: homepage, https://github.com/TUM-Aries-Lab/motor-module
Author-email: Tsmorz <tony.smoragiewicz@tum.de>, Hannes <hannes.nguyen@tum.de>
License-File: LICENSE
Requires-Python: <3.14,>=3.11
Requires-Dist: loguru>=0.7.3
Requires-Dist: numpy>=2.2.3
Requires-Dist: pyserial>=3.5
